{
  "slug": "rnns-vs-transformers-vs-ssms-where-should-ai-memory-live-for-continual-learning",
  "topic": "RNNs vs Transformers vs SSMs: where should AI memory live for continual learning?",
  "title": "Rnns Vs Transformers Vs Ssms: Where Should Ai Memory Live For Continual Learning?",
  "seo_title": "Rnns Vs Transformers Vs Ssms: Where Should Ai Memory Live ",
  "meta_description": "Independent guide to RNNs vs Transformers vs SSMs: where should AI memory live for continual learning?, covering pricing, pros, cons, alternatives, buyer f",
  "canonical": "https://smileaireviewhub.com/rnns-vs-transformers-vs-ssms-where-should-ai-memory-live-for-continual-learning/",
  "status": "READY_FOR_REVIEW",
  "article_type": "comparison",
  "youtube_embed_position": "After introduction or before pricing section",
  "generated_date": "2026-06-29",
  "word_count_estimate": 1669,
  "sections": [
    "Direct Answer",
    "Quick Takeaways",
    "Overview",
    "Best For",
    "Not Best For",
    "Feature Comparison",
    "Pricing Notes",
    "Official Website and Trial Check",
    "Buyer Decision Checklist",
    "Best Use Cases",
    "Pros",
    "Cons",
    "Alternatives",
    "Internal Link Suggestions",
    "Suggested YouTube Embed Position",
    "FAQ",
    "Final Verdict"
  ],
  "internal_link_suggestions": [
    "Closest review page in the same category",
    "One comparison page",
    "One best tools category page",
    "One pricing or free trial guide"
  ],
  "source": "daily_ai_content_factory"
}
